<?xml version="1.0" standalone="yes"?>
<DocumentElement>
  <SpreadTable>
    <iMarker>8</iMarker>
    <_x0020_Projection_x0020_X>0.85274369773545744</_x0020_Projection_x0020_X>
    <_x0020_Projection_x0020_Y>0.92152841359946291</_x0020_Projection_x0020_Y>
  </SpreadTable>
  <SpreadTable>
    <iMarker>9</iMarker>
    <_x0020_Projection_x0020_X>0.48995300006103881</_x0020_Projection_x0020_X>
    <_x0020_Projection_x0020_Y>0.42226698406885188</_x0020_Projection_x0020_Y>
  </SpreadTable>
  <SpreadTable>
    <iMarker>10</iMarker>
    <_x0020_Projection_x0020_X>0.17782457425379972</_x0020_Projection_x0020_X>
    <_x0020_Projection_x0020_Y>0.48594884941707872</_x0020_Projection_x0020_Y>
  </SpreadTable>
  <SpreadTable>
    <iMarker>15</iMarker>
    <_x0020_Projection_x0020_X>-0.11552829152169931</_x0020_Projection_x0020_X>
    <_x0020_Projection_x0020_Y>0.18737105536226573</_x0020_Projection_x0020_Y>
  </SpreadTable>
  <SpreadTable>
    <iMarker>16</iMarker>
    <_x0020_Projection_x0020_X>-0.55625953732527622</_x0020_Projection_x0020_X>
    <_x0020_Projection_x0020_Y>0.26852224867240432</_x0020_Projection_x0020_Y>
  </SpreadTable>
  <SpreadTable>
    <iMarker>27</iMarker>
    <_x0020_Projection_x0020_X>0.64501617530366839</_x0020_Projection_x0020_X>
    <_x0020_Projection_x0020_Y>-0.88291521699322473</_x0020_Projection_x0020_Y>
  </SpreadTable>
  <SpreadTable>
    <iMarker>31</iMarker>
    <_x0020_Projection_x0020_X>0.016211926997497475</_x0020_Projection_x0020_X>
    <_x0020_Projection_x0020_Y>-0.77717756210706224</_x0020_Projection_x0020_Y>
  </SpreadTable>
  <SpreadTable>
    <iMarker>17</iMarker>
    <_x0020_Projection_x0020_X>-0.9971983153268632</_x0020_Projection_x0020_X>
    <_x0020_Projection_x0020_Y>0.93551242141243973</_x0020_Projection_x0020_Y>
  </SpreadTable>
  <SpreadTable>
    <iMarker>32</iMarker>
    <_x0020_Projection_x0020_X>0.5839223585423915</_x0020_Projection_x0020_X>
    <_x0020_Projection_x0020_Y>0.25847524873344319</_x0020_Projection_x0020_Y>
  </SpreadTable>
  <SpreadTable>
    <iMarker>34</iMarker>
    <_x0020_Projection_x0020_X>0.35635109564792766</_x0020_Projection_x0020_X>
    <_x0020_Projection_x0020_Y>-0.85680278337300864</_x0020_Projection_x0020_Y>
  </SpreadTable>
  <SpreadTable>
    <iMarker>35</iMarker>
    <_x0020_Projection_x0020_X>0.18760910700115976</_x0020_Projection_x0020_X>
    <_x0020_Projection_x0020_Y>-0.99526338277482751</_x0020_Projection_x0020_Y>
  </SpreadTable>
  <SpreadTable>
    <iMarker>36</iMarker>
    <_x0020_Projection_x0020_X>-0.50981505218824386</_x0020_Projection_x0020_X>
    <_x0020_Projection_x0020_Y>0.73094671305621683</_x0020_Projection_x0020_Y>
  </SpreadTable>
  <SpreadTable>
    <iMarker>33</iMarker>
    <_x0020_Projection_x0020_X>0.2207593236891901</_x0020_Projection_x0020_X>
    <_x0020_Projection_x0020_Y>0.030202038698651089</_x0020_Projection_x0020_Y>
  </SpreadTable>
  <SpreadTable>
    <iMarker>37</iMarker>
    <_x0020_Projection_x0020_X>0.36284563266800962</_x0020_Projection_x0020_X>
    <_x0020_Projection_x0020_Y>-0.31563205762070429</_x0020_Projection_x0020_Y>
  </SpreadTable>
  <SpreadTable>
    <iMarker>38</iMarker>
    <_x0020_Projection_x0020_X>0.052395776109381689</_x0020_Projection_x0020_X>
    <_x0020_Projection_x0020_Y>0.12244399682597817</_x0020_Projection_x0020_Y>
  </SpreadTable>
  <SpreadTable>
    <iMarker>40</iMarker>
    <_x0020_Projection_x0020_X>-0.99584935603979741</_x0020_Projection_x0020_X>
    <_x0020_Projection_x0020_Y>-0.40828908014405174</_x0020_Projection_x0020_Y>
  </SpreadTable>
</DocumentElement>